{
  "alarm.alarm1": {
    "category": "block",
    "subtitle": "subtitles.lockdown.alarm",
      "sounds": [
        "lockdown:alarm/alarm1"
      ]
  },
  "alarm.alarm2": {
    "category": "block",
    "subtitle": "subtitles.lockdown.alarm",
      "sounds": [
        "lockdown:alarm/alarm2"
      ]
  },
  "alarm.industrial_alarm": {
    "category": "block",
    "subtitle": "subtitles.lockdown.alarm",
      "sounds": [
        "lockdown:alarm/industrial_alarm"
      ],
    "attribution": "TODO: Where is this from?"
  },
  "entity.drone.target": {
    "category": "neutral",
    "subtitle": "subtitles.lockdown.drone.target",
      "sounds": [
        "lockdown:drone_target"
      ]
  }
}
